anonymask-1.1.0.dist-info/METADATA
anonymask-1.1.0.dist-info/WHEEL
anonymask/__init__.py
anonymask/__pycache__/__init__.cpython-313.pyc
anonymask/_anonymask.cpython-311-x86_64-linux-gnu.so
anonymask-1.1.0.dist-info/RECORD
