Metadata-Version: 2.4
Name: anonymask
Version: 1.1.0
Classifier: Development Status :: 4 - Beta
Classifier: Intended Audience :: Developers
Classifier: License :: OSI Approved :: MIT License
Classifier: Operating System :: OS Independent
Classifier: Programming Language :: Python :: 3
Classifier: Programming Language :: Python :: 3.8
Classifier: Programming Language :: Python :: 3.9
Classifier: Programming Language :: Python :: 3.10
Classifier: Programming Language :: Python :: 3.11
Classifier: Programming Language :: Python :: 3.12
Classifier: Programming Language :: Python :: 3.13
Classifier: Programming Language :: Python :: Implementation :: CPython
Classifier: Topic :: Security
Classifier: Topic :: Software Development :: Libraries :: Python Modules
Summary: Secure anonymization/de-anonymization library for PII data
Keywords: anonymization,PII,privacy,LLM,RAG,security
Author-email: Gokul Viswanathan <gokulviswanathan25@gmail.com>
Maintainer-email: Gokul Viswanathan <gokulviswanathan25@gmail.com>
License: MIT
Requires-Python: >=3.8
Project-URL: Homepage, https://github.com/gokul-viswanathan/anonymask
Project-URL: Documentation, https://github.com/gokul-viswanathan/anonymask#readme
Project-URL: Repository, https://github.com/gokul-viswanathan/anonymask.git
Project-URL: Issues, https://github.com/gokul-viswanathan/anonymask/issues
Project-URL: Changelog, https://github.com/gokul-viswanathan/anonymask/blob/main/CHANGELOG.md
